sygicmaps/__init__.py
sygicmaps/client.py
sygicmaps/input.py
sygicmaps-0.2.5.dev0.dist-info/DESCRIPTION.rst
sygicmaps-0.2.5.dev0.dist-info/METADATA
sygicmaps-0.2.5.dev0.dist-info/RECORD
sygicmaps-0.2.5.dev0.dist-info/WHEEL
sygicmaps-0.2.5.dev0.dist-info/metadata.json
sygicmaps-0.2.5.dev0.dist-info/top_level.txt
