Metadata-Version: 2.0
Name: sygicmaps
Version: 0.2.5.dev0
Summary: Python client library Sygic maps services.
Home-page: https://github.com/Sygic/sygic-maps-services-python
Author: UNKNOWN
Author-email: UNKNOWN
License: MIT
Platform: Windows
Classifier: Development Status :: 3 - Alpha
Classifier: Intended Audience :: Developers
Classifier: Topic :: Software Development
Classifier: License :: OSI Approved :: MIT License
Classifier: Programming Language :: Python :: 3.6
Requires-Dist: requests
